setup.py
tears.py
tears.egg-info/PKG-INFO
tears.egg-info/SOURCES.txt
tears.egg-info/dependency_links.txt
tears.egg-info/requires.txt
tears.egg-info/top_level.txt