Metadata-Version: 1.1
Name: tears
Version: 0.3
Summary: SQLAlchemy single connection strategy overwrite to run tests in a super transaction and rollback at teardown.
Home-page: UNKNOWN
Author: Florian Mounier
Author-email: florian.mounier@kozea.fr
License: GPLv3
Platform: Any
Classifier: Development Status :: 4 - Beta
Classifier: Intended Audience :: Developers
Classifier: Operating System :: OS Independent
Classifier: Programming Language :: Python :: 2
Classifier: Programming Language :: Python :: 3
Provides: tears
